{
  "defaultpropertieslanguage": "en",
  "msrcseverity": "Moderate",
  "isbeta": "false",
  "installationbehavior": {},
  "language": [
    {
      "text": "en"
    },
    {
      "text": "zh-tw"
    },
    {
      "text": "ru"
    },
    {
      "text": "sv"
    },
    {
      "text": "ko"
    },
    {
      "text": "zh-cn"
    },
    {
      "text": "es"
    },
    {
      "text": "tr"
    },
    {
      "text": "pt"
    },
    {
      "text": "it"
    },
    {
      "text": "nl"
    },
    {
      "text": "fr"
    },
    {
      "text": "pt-br"
    },
    {
      "text": "ja"
    },
    {
      "text": "cs"
    },
    {
      "text": "de"
    },
    {
      "text": "hu"
    },
    {
      "text": "pl"
    }
  ],
  "supporturl": {
    "text": "http://support.microsoft.com"
  },
  "securitybulletinid": {
    "text": "MS13-090"
  },
  "kbarticleid": {
    "text": "2900986"
  },
  "uninstallationbehavior": {}
}
