{
	"defaultpropertieslanguage": "en",
	"msrcseverity": "Moderate",
	"isbeta": "false",
	"installationbehavior": {},
	"language": [
		{
			"text": "en"
		},
		{
			"text": "sv"
		},
		{
			"text": "tr"
		},
		{
			"text": "ru"
		},
		{
			"text": "pt"
		},
		{
			"text": "pl"
		},
		{
			"text": "nl"
		},
		{
			"text": "cs"
		},
		{
			"text": "zh-tw"
		},
		{
			"text": "hu"
		},
		{
			"text": "fr"
		},
		{
			"text": "ja"
		},
		{
			"text": "ko"
		},
		{
			"text": "de"
		},
		{
			"text": "it"
		},
		{
			"text": "zh-cn"
		},
		{
			"text": "es"
		},
		{
			"text": "pt-br"
		}
	],
	"supporturl": {
		"text": "http://support.microsoft.com"
	},
	"securitybulletinid": {
		"text": "MS14-084"
	},
	"kbarticleid": {
		"text": "3012172"
	},
	"uninstallationbehavior": {}
}
