{
	"defaultpropertieslanguage": "en",
	"msrcseverity": "Critical",
	"isbeta": "false",
	"installationbehavior": {},
	"language": [
		{
			"text": "en"
		},
		{
			"text": "pl"
		},
		{
			"text": "ru"
		},
		{
			"text": "sv"
		},
		{
			"text": "tr"
		},
		{
			"text": "pt"
		},
		{
			"text": "pt-br"
		},
		{
			"text": "ja"
		},
		{
			"text": "it"
		},
		{
			"text": "de"
		},
		{
			"text": "ko"
		},
		{
			"text": "nl"
		},
		{
			"text": "no"
		},
		{
			"text": "fr"
		},
		{
			"text": "hu"
		},
		{
			"text": "he"
		},
		{
			"text": "es"
		},
		{
			"text": "fi"
		},
		{
			"text": "zh-tw"
		},
		{
			"text": "da"
		},
		{
			"text": "el"
		},
		{
			"text": "ar"
		},
		{
			"text": "cs"
		},
		{
			"text": "zh-cn"
		}
	],
	"supporturl": {
		"text": "http://support.microsoft.com"
	},
	"securitybulletinid": {
		"text": "MS15-032"
	},
	"kbarticleid": {
		"text": "3038314"
	},
	"uninstallationbehavior": {}
}
