{
	"creationdate": "2017-06-27T00:14:42Z",
	"defaultlanguage": "en",
	"updateid": "2276cdb8-ddfb-476a-b48c-89342713b63c",
	"revisionid": "16448407",
	"isleaf": "true",
	"isbundle": "true",
	"categories": {
		"category": [
			{
				"type": "UpdateClassification",
				"id": "0fa1201d-4330-4fa8-8ae9-b877473b6441"
			},
			{
				"type": "Company",
				"id": "56309036-4c77-4dd9-951a-99ee9c246a94"
			},
			{
				"type": "ProductFamily",
				"id": "6964aab4-c5b5-43bd-a17d-ffb4346a8e1d"
			},
			{
				"type": "Product",
				"id": "f4b9c883-f4db-4fb5-b204-3343c11fa021"
			}
		]
	},
	"languages": {},
	"supersededby": {
		"revision": [
			{
				"id": "37886321"
			},
			{
				"id": "27475176"
			},
			{
				"id": "32510918"
			},
			{
				"id": "29645129"
			},
			{
				"id": "37726642"
			},
			{
				"id": "36766272"
			},
			{
				"id": "35115997"
			},
			{
				"id": "27741522"
			},
			{
				"id": "30037618"
			},
			{
				"id": "30093315"
			},
			{
				"id": "38812977"
			},
			{
				"id": "39373331"
			},
			{
				"id": "36989139"
			},
			{
				"id": "33401900"
			},
			{
				"id": "29405681"
			},
			{
				"id": "27910079"
			},
			{
				"id": "31907301"
			},
			{
				"id": "30238269"
			},
			{
				"id": "34468152"
			},
			{
				"id": "32135665"
			},
			{
				"id": "38252627"
			},
			{
				"id": "32312631"
			},
			{
				"id": "32709492"
			},
			{
				"id": "34880562"
			},
			{
				"id": "38454445"
			},
			{
				"id": "30008045"
			},
			{
				"id": "30044318"
			},
			{
				"id": "33570413"
			},
			{
				"id": "38632277"
			},
			{
				"id": "35532363"
			},
			{
				"id": "34663859"
			},
			{
				"id": "34709313"
			},
			{
				"id": "32930122"
			},
			{
				"id": "33802142"
			},
			{
				"id": "28127080"
			},
			{
				"id": "28535520"
			},
			{
				"id": "39192776"
			},
			{
				"id": "37569573"
			},
			{
				"id": "38087235"
			},
			{
				"id": "38980587"
			},
			{
				"id": "31265163"
			},
			{
				"id": "31534765"
			},
			{
				"id": "28984345"
			},
			{
				"id": "36589757"
			},
			{
				"id": "30407161"
			},
			{
				"id": "33126918"
			},
			{
				"id": "35763779"
			},
			{
				"id": "31031164"
			},
			{
				"id": "29862904"
			},
			{
				"id": "37189082"
			},
			{
				"id": "29213232"
			},
			{
				"id": "30659816"
			},
			{
				"id": "35993096"
			},
			{
				"id": "34268053"
			},
			{
				"id": "28377874"
			},
			{
				"id": "31703783"
			},
			{
				"id": "28720120"
			},
			{
				"id": "28757160"
			},
			{
				"id": "36153574"
			},
			{
				"id": "34053000"
			},
			{
				"id": "37359984"
			},
			{
				"id": "35313402"
			},
			{
				"id": "27298096"
			},
			{
				"id": "27072660"
			},
			{
				"id": "32718364"
			},
			{
				"id": "36364536"
			}
		]
	}
}
