{
	"creationdate": "2019-10-08T00:18:38Z",
	"defaultlanguage": "en",
	"updateid": "2d878ad9-f5a7-4054-a654-f403185daed1",
	"revisionid": "30032524",
	"isleaf": "true",
	"isbundle": "true",
	"categories": {
		"category": [
			{
				"type": "UpdateClassification",
				"id": "0fa1201d-4330-4fa8-8ae9-b877473b6441"
			},
			{
				"type": "Company",
				"id": "56309036-4c77-4dd9-951a-99ee9c246a94"
			},
			{
				"type": "ProductFamily",
				"id": "6964aab4-c5b5-43bd-a17d-ffb4346a8e1d"
			},
			{
				"type": "Product",
				"id": "a3c2375d-0c8a-42f9-bce0-28333e198407"
			}
		]
	},
	"languages": {},
	"supersededby": {
		"revision": [
			{
				"id": "30238112"
			},
			{
				"id": "32135227"
			},
			{
				"id": "32746347"
			},
			{
				"id": "34268535"
			},
			{
				"id": "31907079"
			},
			{
				"id": "31264983"
			},
			{
				"id": "34053427"
			}
		]
	}
}
