{
	"creationdate": "2017-06-27T00:34:34Z",
	"defaultlanguage": "en",
	"updateid": "3e5b9fb3-5ad4-493c-813d-7dd06d3f1dab",
	"revisionid": "12408313",
	"isleaf": "true",
	"isbundle": "true",
	"categories": {
		"category": [
			{
				"type": "UpdateClassification",
				"id": "0fa1201d-4330-4fa8-8ae9-b877473b6441"
			},
			{
				"type": "Company",
				"id": "56309036-4c77-4dd9-951a-99ee9c246a94"
			},
			{
				"type": "ProductFamily",
				"id": "6964aab4-c5b5-43bd-a17d-ffb4346a8e1d"
			},
			{
				"type": "Product",
				"id": "d31bd4c3-d872-41c9-a2e7-231f372588cb"
			}
		]
	},
	"languages": {},
	"supersededby": {
		"revision": [
			{
				"id": "41413836"
			},
			{
				"id": "31031138"
			},
			{
				"id": "41025601"
			},
			{
				"id": "40843191"
			},
			{
				"id": "41917780"
			},
			{
				"id": "41752594"
			},
			{
				"id": "42062332"
			},
			{
				"id": "42259048"
			},
			{
				"id": "21803562"
			},
			{
				"id": "41239288"
			},
			{
				"id": "40696437"
			},
			{
				"id": "33401987"
			},
			{
				"id": "41573975"
			}
		]
	}
}
