{
  "creationdate": "2017-06-27T00:43:04Z",
  "defaultlanguage": "en",
  "updateid": "5619ba1e-ca11-413a-91e3-dfb8c883daa6",
  "revisionid": "4976746",
  "isleaf": "true",
  "isbundle": "true",
  "categories": {
    "category": [
      {
        "type": "UpdateClassification",
        "id": "0fa1201d-4330-4fa8-8ae9-b877473b6441"
      },
      {
        "type": "ProductFamily",
        "id": "477b856e-65c4-4473-b621-a8b230bb70d9"
      },
      {
        "type": "Company",
        "id": "56309036-4c77-4dd9-951a-99ee9c246a94"
      },
      {
        "type": "Product",
        "id": "6248b8b1-ffeb-dbd9-887a-2acf53b09dfe"
      }
    ]
  },
  "languages": {},
  "supersededby": {
    "revision": [
      {
        "id": "4981989"
      },
      {
        "id": "4977463"
      },
      {
        "id": "4979183"
      },
      {
        "id": "4981168"
      },
      {
        "id": "4981727"
      },
      {
        "id": "4981310"
      }
    ]
  }
}
