{
	"language": {
		"text": "en"
	},
	"title": {
		"text": "Security Update for .NET Framework 2.0 SP2 and 3.5 SP1 on Windows Server 2003 and Windows XP for x64-based Systems (KB2446704)\n"
	},
	"description": {
		"text": "A security issue has been identified that could allow an attacker to compromise your Windows-based system that is running the Microsoft .NET Framework and gain complete control over it. You can help protect your computer by installing this update from Microsoft. After you install this item, you may have to restart your computer."
	}
}
